LICENSE
MANIFEST.in
README.rst
setup.py
automatepy/__init__.py
automatepy/alarm.py
automatepy/countdown.py
automatepy.egg-info/PKG-INFO
automatepy.egg-info/SOURCES.txt
automatepy.egg-info/dependency_links.txt
automatepy.egg-info/top_level.txt
automatepy/assets/alarm.wav