Metadata-Version: 1.1
Name: automatepy
Version: 0.1.1
Summary: A simple python app for automation.
Home-page: UNKNOWN
Author: hchockarprasad
Author-email: hchockarprasad@gmail.com
License: MIT License
Platform: UNKNOWN
Classifier: Operating System :: OS Independent
Classifier: Programming Language :: Python
Classifier: Programming Language :: Python :: 3.5
